lawsql_cases_raw/__init__.py
lawsql_cases_raw/__main__.py
lawsql_cases_raw/api.py
lawsql_cases_raw/config.py
lawsql_cases_raw/dockets.py
lawsql_cases_raw/fetcher.py
lawsql_cases_raw/organizer.py
lawsql_cases_raw/raw_sql/__init__.py
lawsql_cases_raw/raw_sql/dup_dockets.py
lawsql_cases_raw/raw_sql/dup_phils.py
lawsql_cases_raw/reports.py
lawsql_cases_raw/tables/__init__.py
lawsql_cases_raw/tables/decisions.py
lawsql_cases_raw/tables/voting_lines.py
lawsql_cases_raw/utils.py
lawsql_cases_raw/voting/__init__.py
lawsql_cases_raw/voting/lines.py
lawsql_cases_raw-0.0.11.dist-info/WHEEL
lawsql_cases_raw-0.0.11.dist-info/METADATA
lawsql_cases_raw-0.0.11.dist-info/RECORD
