Metadata-Version: 2.1
Name: lawsql-cases-raw
Version: 0.0.11
Summary: Get decision data from .html and yaml files; updates local database with field lookups.
Author: Marcelino G. Veloso III
Author-email: mars@veloso.one
Requires-Python: >=3.9,<4.0
Classifier: Programming Language :: Python :: 3
Classifier: Programming Language :: Python :: 3.9
Classifier: Programming Language :: Python :: 3.10
Requires-Dist: PyYAML (>=6.0,<7.0)
Requires-Dist: Unidecode (>=1.3.0,<2.0.0)
Requires-Dist: citation-decision (>=0.0.3,<0.0.4)
Requires-Dist: httpx (>=0.22.0,<0.23.0)
Requires-Dist: lawsql-cases-justices (>=0.0.5,<0.0.6)
Requires-Dist: sqlite-utils (>=3.26,<4.0)
